SnowFox
